ExpoSeq/__init__.py
ExpoSeq/pipeline.py
ExpoSeq/augment_data/__init__.py
ExpoSeq/augment_data/binding_data.py
ExpoSeq/augment_data/check_reports.py
ExpoSeq/augment_data/collect_fastqs.py
ExpoSeq/augment_data/create_mixcr_commands.py
ExpoSeq/augment_data/load_data.py
ExpoSeq/augment_data/loop_collect_reports.py
ExpoSeq/augment_data/mixcr_cl.py
ExpoSeq/augment_data/mixcr_nils.py
ExpoSeq/augment_data/preset_chooser.py
ExpoSeq/augment_data/randomizer.py
ExpoSeq/augment_data/read_raw_data.py
ExpoSeq/augment_data/structure_files.py
ExpoSeq/augment_data/trimming.py
ExpoSeq/augment_data/uploader.py
ExpoSeq/design/__init__.py
ExpoSeq/design/anno_sequence.py
ExpoSeq/design/msa_design.py
ExpoSeq/design/multi_seq_align.py
ExpoSeq/design/utilize_af.py
ExpoSeq/plots/__init__.py
ExpoSeq/plots/attention_heatmap.py
ExpoSeq/plots/barplot.py
ExpoSeq/plots/clone_fraction.py
ExpoSeq/plots/colors_logoplot.py
ExpoSeq/plots/diversity_plot.py
ExpoSeq/plots/global_font.py
ExpoSeq/plots/hist_lvst_dist.py
ExpoSeq/plots/hist_lvst_dist_bind.py
ExpoSeq/plots/length_clone_fraction.py
ExpoSeq/plots/length_distribution.py
ExpoSeq/plots/levenshtein_clustering.py
ExpoSeq/plots/logo_plot.py
ExpoSeq/plots/multiple_length_plot.py
ExpoSeq/plots/protein_embedding.py
ExpoSeq/plots/protein_embedding_umap.py
ExpoSeq/plots/protein_network_embedding.py
ExpoSeq/plots/rarefraction_curves.py
ExpoSeq/plots/sample_cluster.py
ExpoSeq/plots/saveFig.py
ExpoSeq/plots/stacked_aa_distribution.py
ExpoSeq/plots/tidy_protbert_embedding.py
ExpoSeq/plots/contents/__init__.py
ExpoSeq/plots/contents/contact_prediction.py
ExpoSeq/plots/contents/hytdrophobicity_metrics.py
ExpoSeq/plots/contents/isoelectric_point_scales.py
ExpoSeq/plots/contents/simple_protein_property.py
ExpoSeq/plots/deprecated/__init__.py
ExpoSeq/plots/deprecated/bert_network_embedding.py
ExpoSeq/plots/deprecated/cluster_embedding.py
ExpoSeq/plots/deprecated/cluster_multiple_antigens.py
ExpoSeq/plots/deprecated/embedding_with_binding.py
ExpoSeq-4.6.1.dist-info/LICENSE
ExpoSeq-4.6.1.dist-info/METADATA
ExpoSeq-4.6.1.dist-info/WHEEL
ExpoSeq-4.6.1.dist-info/top_level.txt
ExpoSeq-4.6.1.dist-info/RECORD
