Metadata-Version: 2.1
Name: ExpoSeq
Version: 4.6.1
Summary: A pacakge which provides various ways to analyze NGS data from phage display campaigns
Home-page: https://github.com/nilshof01/ExpoSeq
Author: Nils Hofmann
Author-email: Nils Hofmann <nilhof01@gmail.com>
License: LICENCE
Project-URL: Homepage, https://github.com/nilshof01/ExpoSeq
Requires-Python: >=3.8
License-File: LICENSE
Requires-Dist: PyQT6
Requires-Dist: PyQT5
Requires-Dist: biopython ==1.80
Requires-Dist: editdistance ==0.6.2
Requires-Dist: logomaker ==0.8
Requires-Dist: markdown
Requires-Dist: matplotlib ==3.7.3
Requires-Dist: networkx ==3.1
Requires-Dist: numpy ==1.23.5
Requires-Dist: openpyxl
Requires-Dist: pandas ==1.5.3
Requires-Dist: pandasai ==1.3.3
Requires-Dist: python-louvain ==0.16
Requires-Dist: scikit-learn >=1.2.1
Requires-Dist: scipy ==1.11.4
Requires-Dist: seaborn ==0.12.2
Requires-Dist: sentencepiece ==0.1.99
Requires-Dist: sgt ==2.0.3
Requires-Dist: squarify ==0.4.3
Requires-Dist: tabulate ==0.9.0
Requires-Dist: torch ==2.1.0
Requires-Dist: transformers ==4.34.1
Requires-Dist: matplotlib-venn
Requires-Dist: umap-learn ==0.5.5
Requires-Dist: iglabel ==0.0.7
Requires-Dist: rjieba
Requires-Dist: protobuf
Requires-Dist: peptides
